synthetic_open_schema_model/__init__.py
synthetic_open_schema_model/base.py
synthetic_open_schema_model/v1beta1/__init__.py
synthetic_open_schema_model/v1beta1/dns.py
synthetic_open_schema_model/v1beta1/http.py
synthetic_open_schema_model/v1beta1/playwright.py
synthetic_open_schema_model/v1beta1/ssl.py
synthetic_open_schema_model/v1beta1/tcp.py
synthetic_open_schema_model-0.1.0.dist-info/METADATA
synthetic_open_schema_model-0.1.0.dist-info/WHEEL
synthetic_open_schema_model-0.1.0.dist-info/RECORD
